dbaas_zabbix/__init__.py
dbaas_zabbix/database_providers.py
dbaas_zabbix/dbaas_api.py
dbaas_zabbix/errors.py
dbaas_zabbix/metrics.py
dbaas_zabbix/provider.py
dbaas_zabbix/provider_factory.py
dbaas_zabbix-0.7.17.dist-info/AUTHORS.rst
dbaas_zabbix-0.7.17.dist-info/LICENSE
dbaas_zabbix-0.7.17.dist-info/METADATA
dbaas_zabbix-0.7.17.dist-info/WHEEL
dbaas_zabbix-0.7.17.dist-info/top_level.txt
dbaas_zabbix-0.7.17.dist-info/RECORD
