Metadata-Version: 2.1
Name: dbaas-zabbix
Version: 0.7.17
Summary: A Zabbix Integration for DBaaS.
Home-page: https://github.com/globocom/dbaas-zabbix
Author: Felippe Raposo
Author-email: raposo.felippe@gmail.com
License: BSD
Keywords: dbaas_zabbix
Classifier: Development Status :: 2 - Pre-Alpha
Classifier: Intended Audience :: Developers
Classifier: License :: OSI Approved :: BSD License
Classifier: Natural Language :: English
Classifier: Programming Language :: Python :: 2
Classifier: Programming Language :: Python :: 2.6
Classifier: Programming Language :: Python :: 2.7
Classifier: Programming Language :: Python :: 3
Classifier: Programming Language :: Python :: 3.3
License-File: LICENSE
License-File: AUTHORS.rst
Requires-Dist: pyzabbix
